cloud_maker/__init__.py
cloud_maker/__main__.py
cloud_maker/py_version.py
cloud_maker-0.8.4.dist-info/DESCRIPTION.rst
cloud_maker-0.8.4.dist-info/METADATA
cloud_maker-0.8.4.dist-info/RECORD
cloud_maker-0.8.4.dist-info/WHEEL
cloud_maker-0.8.4.dist-info/entry_points.txt
cloud_maker-0.8.4.dist-info/metadata.json
cloud_maker-0.8.4.dist-info/top_level.txt
fedora2ova/__init__.py
fedora2ova/__main__.py
fedora2ova/app.py
fedora2ova/tempdir.py
fedora2ova/resources/epilog.txt
fedora2ova/resources/meta-data.yaml
fedora2ova/resources/user-data.yaml
make_provisioner/__init__.py
make_provisioner/__main__.py
make_provisioner/app.py
make_provisioner/data.py
make_provisioner/template.py
make_provisioner/scripts/guest.sh
