Metadata-Version: 2.0
Name: cloud-maker
Version: 0.8.4
Summary: Tools for building cloud images (make_provisioner and fedora2ova)
Home-page: https://github.com/sapphirecat/cloud-maker
Author: Sapphire Cat
Author-email: devel@sapphirepaw.org
License: MIT
Keywords: aws cloud ami packer provisioner devops
Platform: UNKNOWN
Classifier: Development Status :: 4 - Beta
Classifier: Environment :: Console
Classifier: Operating System :: OS Independent
Classifier: Intended Audience :: Developers
Classifier: Intended Audience :: System Administrators
Classifier: Topic :: System :: Installation/Setup
Classifier: License :: OSI Approved :: MIT License
Classifier: Programming Language :: Python :: 2
Classifier: Programming Language :: Python :: 2.7
Classifier: Programming Language :: Python :: 3
Classifier: Programming Language :: Python :: 3.3
Classifier: Programming Language :: Python :: 3.4
Classifier: Programming Language :: Python :: 3.5
